jvgraph/__init__.py
jvgraph/cli.py
jvgraph/group.py
jvgraph/commands/__init__.py
jvgraph/commands/launch.py
jvgraph/studio/index.html
jvgraph/studio/jac_logo.png
jvgraph/studio/tauri.svg
jvgraph/studio/vite.svg
jvgraph/studio/assets/index-DDV79SDu.js
jvgraph/studio/assets/index-DdMMONxd.css
jvgraph/studio-auth/index.html
jvgraph/studio-auth/jac_logo.png
jvgraph/studio-auth/tauri.svg
jvgraph/studio-auth/vite.svg
jvgraph/studio-auth/assets/index-Bh6lyeXA.js
jvgraph/studio-auth/assets/index-DdMMONxd.css
jvgraph-2.1.0.dist-info/licenses/LICENSE
jvgraph-2.1.0.dist-info/METADATA
jvgraph-2.1.0.dist-info/WHEEL
jvgraph-2.1.0.dist-info/entry_points.txt
jvgraph-2.1.0.dist-info/top_level.txt
jvgraph-2.1.0.dist-info/RECORD
