Metadata-Version: 2.4
Name: jvgraph
Version: 2.1.0
Summary: CLI tool for Jivas Graph
Home-page: https://github.com/TrueSelph/jvgraph
Author: TrueSelph Inc.
Author-email: admin@trueselph.com
Requires-Python: >=3.12
License-File: LICENSE
Requires-Dist: click>=8.1.8
Requires-Dist: requests>=2.32.3
Requires-Dist: packaging>=24.2
Requires-Dist: pyaml>=25.1.0
Requires-Dist: jac-cloud==0.2.3
Requires-Dist: streamlit>=1.42.0
Requires-Dist: streamlit-elements>=0.1.0
Requires-Dist: streamlit-router>=0.1.8
Requires-Dist: streamlit-javascript>=0.1.5
Requires-Dist: python-dotenv>=1.0.0
Requires-Dist: semver>=3.0.4
Requires-Dist: node-semver>=0.9.0
Provides-Extra: dev
Requires-Dist: pre-commit; extra == "dev"
Requires-Dist: pytest; extra == "dev"
Requires-Dist: pytest-mock; extra == "dev"
Requires-Dist: pytest-cov; extra == "dev"
Dynamic: author
Dynamic: author-email
Dynamic: description
Dynamic: description-content-type
Dynamic: home-page
Dynamic: license-file
Dynamic: provides-extra
Dynamic: requires-dist
Dynamic: requires-python
Dynamic: summary
